{"stat.craftItem.69":1,"stat.useItem.355":2,"stat.craftItem.61":3,"stat.leaveGame":8,"stat.mineBlock.14":3,"stat.mineBlock.13":115,"stat.mineBlock.16":99,"stat.mineBlock.15":69,"stat.mineBlock.18":38,"stat.mineBlock.17":31,"stat.swimOneCm":72033,"stat.craftItem.333":6,"stat.useItem.128":63,"stat.climbOneCm":12394,"stat.craftItem.72":1,"achievement.buildWorkBench":11,"stat.craftItem.324":5,"stat.craftItem.325":1,"achievement.exploreAllBiomes":{"value":0,"progress":["Sunflower Plains","Savanna Plateau","ForestHills","Magical Forest","Flower Forest","Plains","Beach","DesertHills","Stone Beach","Eerie","Extreme Hills+","Forest","River","Ocean","Taiga","Desert","Extreme Hills","Swampland","Deep Ocean","Savanna"]},"stat.mineBlock.12":665,"tconstruct.smelteryMaker":34,"stat.craftItem.366":2,"stat.entityKilledBy.Spider":2,"stat.craftItem.85":10,"stat.mineBlock.4":26,"stat.mineBlock.111":3,"stat.mineBlock.5":1,"stat.mineBlock.3":380,"stat.mineBlock.1":1469,"stat.killEntity.Enderman":3,"stat.flyOneCm":906024,"stat.craftItem.351":6,"stat.craftItem.355":1,"achievement.buildPickaxe":13,"achievement.buildBetterPickaxe":13,"stat.mineBlock.128":8,"ic2.mineOre":161,"stat.craftItem.24":96,"ic2.acquireResin":22,"stat.mineBlock.175":3,"stat.killEntity.Creeper":6,"tconstruct.beginner":3,"stat.useItem.324":8,"stat.useItem.323":2,"stat.entityKilledBy.Skeleton":6,"achievement.buildSword":5,"achievement.mineWood":73,"stat.breakItem.272":1,"stat.craftItem.323":6,"stat.useItem.85":9,"stat.breakItem.274":10,"achievement.openInventory":410,"stat.breakItem.273":4,"stat.breakItem.275":2,"stat.mineBlock.161":8,"stat.mineBlock.162":63,"stat.entityKilledBy.Creeper":1,"achievement.killEnemy":89,"stat.craftItem.58":9,"stat.deaths":22,"stat.drop":627,"stat.playOneMinute":822910,"stat.craftItem.50":200,"stat.killEntity.Sheep":18,"stat.craftItem.54":7,"stat.killEntity.Zombie":48,"stat.diveOneCm":38313,"stat.useItem.61":9,"achievement.buildHoe":1,"stat.breakItem.257":5,"stat.mineBlock.81":2,"stat.mineBlock.82":30,"stat.useItem.72":1,"stat.jump":7221,"stat.fallOneCm":145219,"stat.craftItem.291":1,"stat.craftItem.171":3,"achievement.killCow":11,"stat.useItem.45":5,"stat.boatOneCm":307654,"stat.craftItem.5":128,"stat.damageTaken":23047,"stat.mineBlock.61":10,"stat.mineBlock.66":1,"stat.killEntity.CaveSpider":2,"stat.useItem.54":8,"stat.useItem.50":179,"stat.entityKilledBy.Zombie":4,"stat.damageDealt":45815,"stat.killEntity.Cow":22,"stat.killEntity.Pig":50,"stat.mineBlock.73":11,"stat.useItem.58":14,"stat.useItem.274":1286,"stat.useItem.20":43,"stat.useItem.273":621,"stat.mineBlock.46":9,"stat.useItem.275":301,"stat.walkOneCm":5470102,"stat.craftItem.265":26,"stat.craftItem.266":12,"stat.useItem.156":1,"stat.craftItem.267":2,"stat.animalsBred":1,"stat.playerKills":1,"stat.craftItem.258":1,"stat.useItem.24":1025,"stat.mineBlock.45":7,"stat.mineBlock.58":7,"stat.craftItem.256":0,"stat.craftItem.257":6,"stat.breakItem.314":1,"stat.mineBlock.102":3,"stat.craftItem.126":6,"stat.mineBlock.50":45,"stat.entityKilledBy.Enderman":3,"stat.craftItem.128":56,"stat.useItem.35":5,"stat.mineBlock.54":1,"stat.useItem.291":91,"stat.mineBlock.56":2,"stat.mineBlock.24":856,"stat.killEntity.Skeleton":27,"stat.useItem.256":283,"stat.useItem.258":113,"stat.useItem.257":1716,"stat.killEntity.Chicken":8,"stat.craftItem.280":156,"stat.killEntity.Spider":18,"stat.breakItem.306":1,"stat.mobKills":215,"stat.mineBlock.21":4,"stat.mineBlock.20":20,"stat.craftItem.272":2,"stat.craftItem.273":6,"stat.mineBlock.35":3,"stat.craftItem.274":11,"stat.craftItem.275":3,"stat.useItem.12":218,"stat.useItem.267":280,"stat.useItem.4":282,"stat.useItem.5":13,"stat.useItem.3":177,"stat.mineBlock.30":41,"stat.useItem.391":98,"stat.useItem.13":10,"stat.mineBlock.31":238,"stat.useItem.272":389}